autort
