Metadata-Version: 2.1
Name: autort
Version: 0.1.1
Home-page: https://github.com/microsoft/antares
Author: Microsoft
License: MIT
Keywords: antares autort
Platform: UNKNOWN
Requires-Dist: wheel (>=0.26) ; python_version >= "3"
Requires-Dist: numpy ; python_version >= "3"
Requires-Dist: torch (==2.0.0) ; python_version >= "3"
